ncis/__init__.py
ncis-0.1.dist-info/METADATA
ncis-0.1.dist-info/WHEEL
ncis-0.1.dist-info/top_level.txt
ncis-0.1.dist-info/RECORD
